popfinder/__init__.py
popfinder/_helper.py
popfinder/_mp_testing.py
popfinder/_mp_training.py
popfinder/_multiboots.py
popfinder/_neural_networks.py
popfinder/_version.py
popfinder/_visualize.py
popfinder/classifier.py
popfinder/cli_classifier.py
popfinder/cli_regressor.py
popfinder/dataloader.py
popfinder/regressor.py
tests/__init__.py
tests/test_popfinder.py
popfinder-0.0.6.dist-info/LICENSE
popfinder-0.0.6.dist-info/METADATA
popfinder-0.0.6.dist-info/WHEEL
popfinder-0.0.6.dist-info/entry_points.txt
popfinder-0.0.6.dist-info/top_level.txt
popfinder-0.0.6.dist-info/RECORD
