Metadata-Version: 2.1
Name: popfinder
Version: 0.0.6
Summary: Genetic population assignment using neural networks
Author: Katie Birchard
Author-email: katie.birchard@apexrms.com
License-File: LICENSE
